i18nco/__init__.py
i18nco/constants.py
i18nco/internationalization.py
i18nco/typeins.py
i18nco/utils.py
i18nco-1.5.1.dist-info/LICENSE
i18nco-1.5.1.dist-info/METADATA
i18nco-1.5.1.dist-info/WHEEL
i18nco-1.5.1.dist-info/top_level.txt
i18nco-1.5.1.dist-info/RECORD
